{"subject": "H2 Economics", "paper": "NYJC Chapter 3 Tutorial", "pdf": ["https://github.com/Hackin7/ExamSnippet/blob/master/Questions/A%20Level/H2%20Economics/NYJC%20Chapter%203%20Tutorial/Tutorial.pdf?raw=true"], "questions": [{"subject": "H2 Economics", "paper": "NYJC Chapter 3 Tutorial", "q_id": "3 1a", "topics": ["Microeconomics Essays"], "images": [], "answerImages": [], "pdf": ["https://github.com/Hackin7/ExamSnippet/blob/master/Questions/A%20Level/H2%20Economics/NYJC%20Chapter%203%20Tutorial/Tutorial.pdf?raw=true"], "anspdf": [], "question": "1.   Prices of agricultural products increased by 14% in recent years, compared with only 3% for manufactured goods.(a)   Using  economic  analysis,  account  for  the  differences  in  prices  of  agricultural  and  manufactured products. [10][Suggested Answer on Page 3-10T]", "type": "open", "given": [""], "correct": ["", "", "", "", "", "", "", "", "", ""], "marks": [1, 1, 1, 1, 1, 1, 1, 1, 1, 1], "self_mark": true}, {"subject": "H2 Economics", "paper": "NYJC Chapter 3 Tutorial", "q_id": "3 2a", "topics": ["Microeconomics Essays"], "images": [], "answerImages": [], "pdf": ["https://github.com/Hackin7/ExamSnippet/blob/master/Questions/A%20Level/H2%20Economics/NYJC%20Chapter%203%20Tutorial/Tutorial.pdf?raw=true"], "anspdf": [], "question": "2.    (a) Distinguish    between    price    elasticity    of    demand,    income    elasticity    of          demand and cross elasticity of demand. [10][Suggested Answer on Page 3-12T]", "type": "open", "given": [""], "correct": ["", "", "", "", "", "", "", "", "", ""], "marks": [1, 1, 1, 1, 1, 1, 1, 1, 1, 1], "self_mark": true}, {"subject": "H2 Economics", "paper": "NYJC Chapter 3 Tutorial", "q_id": "3 3a", "topics": ["Microeconomics Essays"], "images": [], "answerImages": [], "pdf": ["https://github.com/Hackin7/ExamSnippet/blob/master/Questions/A%20Level/H2%20Economics/NYJC%20Chapter%203%20Tutorial/Tutorial.pdf?raw=true"], "anspdf": [], "question": "3.    Governments  frequently  impose  indirect  taxes  in  order  to  influence  the  pattern  of  consumers\u2019 expenditure. The effectiveness of such policy measures, however, depends crucially on how consumers respond.(a)  Explain  with  the  help  of  examples  the  concepts  of  price  elasticity  of  demand  and  price elasticity of supply. [10][Suggested Answer on Page 3-13T]", "type": "open", "given": [""], "correct": ["", "", "", "", "", "", "", "", "", ""], "marks": [1, 1, 1, 1, 1, 1, 1, 1, 1, 1], "self_mark": true}]}